zdatabase/__init__.py
zdatabase/mixins.py
zdatabase/model.py
zdatabase/utils/time.py
zdatabase-0.5.21.dist-info/METADATA
zdatabase-0.5.21.dist-info/WHEEL
zdatabase-0.5.21.dist-info/licenses/LICENSE
zdatabase-0.5.21.dist-info/RECORD
