Metadata-Version: 2.1
Name: zdatabase
Version: 0.5.21
Summary: zen database library
Project-URL: Homepage, https://github.com/inspirare6/zdatabase
Project-URL: Bug Tracker, https://github.com/inspirare6/zdatabase/issues
Author-email: inspirare6 <inspirare6@163.com>
License-File: LICENSE
Classifier: License :: OSI Approved :: MIT License
Classifier: Operating System :: OS Independent
Classifier: Programming Language :: Python :: 3
Requires-Python: >=3.7
Requires-Dist: arrow==0.17.0
Requires-Dist: flask-sqlalchemy==2.5.1
Requires-Dist: jsonschema==4.17.3
Requires-Dist: sqlalchemy==1.4.39
